Metadata-Version: 2.1
Name: wzdx-translator-jacob6838
Version: 0.4.5
Summary: CDOT Work Zone WZDx Translators
Author: Jacob Frye
Author-email: jfrye@neaeraconsulting.com
Keywords: python,wzdx
Classifier: Development Status :: 4 - Beta
Classifier: Programming Language :: Python :: 3
Classifier: Operating System :: Microsoft :: Windows
License-File: LICENSE.md
Requires-Dist: xmltodict
Requires-Dist: jsonschema
Requires-Dist: python-dateutil
Requires-Dist: shapely
Requires-Dist: geopy
Requires-Dist: pyproj
Requires-Dist: numpy
Requires-Dist: requests
Requires-Dist: pytz
